aframe/__init__.py
aframe/a_html.py
aframe/core.py
aframe/examples/with_fastapi.py
aframe/helpers.py
aframe/templates.py
aframe-0.1.0.dist-info/WHEEL
aframe-0.1.0.dist-info/METADATA
aframe-0.1.0.dist-info/RECORD
