Metadata-Version: 2.1
Name: aframe
Version: 0.1.0
Summary: 
Author: MBeebe
Author-email: pyn-sol@beebe.dev
Requires-Python: >=3.8,<4.0
Classifier: Programming Language :: Python :: 3
Classifier: Programming Language :: Python :: 3.10
Classifier: Programming Language :: Python :: 3.8
Classifier: Programming Language :: Python :: 3.9
Requires-Dist: beautifulsoup4 (>=4.11.1,<5.0.0)
Requires-Dist: inline-example (>=0.1.1,<0.2.0)
Requires-Dist: requests (>=2.28.1,<3.0.0)
